{"v":"5.6.10","fr":60,"ip":0,"op":120,"w":400,"h":280,"nm":"transition-2-to-3  at 1024","ddd":0,"assets":[{"id":"image_0","w":88,"h":88,"u":"images/","p":"quickbooks.intuit.com/cas/dam/IMAGE/A1PB5ujrK/owner-avatar-1.png","e":0}],"layers":[{"ddd":0,"ind":1,"ty":2,"nm":"quickbooks.intuit.com/cas/dam/IMAGE/A1PB5ujrK/owner-avatar-1.png","cl":"png","refId":"image_0","sr":1,"ks":{"o":{"a":1,"k":[{"i":{"x":[0.833],"y":[0.833]},"o":{"x":[0.167],"y":[0.167]},"t":101,"s":[100]},{"t":119,"s":[0]}]},"p":{"s":true,"x":{"a":1,"k":[{"i":{"x":[0.667],"y":[1]},"o":{"x":[0.333],"y":[0]},"t":0,"s":[45]},{"t":72,"s":[282]}]},"y":{"a":1,"k":[{"i":{"x":[0.667],"y":[1]},"o":{"x":[0.333],"y":[0]},"t":0,"s":[226]},{"t":72,"s":[209]}]}},"a":{"a":0,"k":[44,44,0]},"s":{"a":1,"k":[{"i":{"x":[0.667,0.667,0.667],"y":[1,1,1]},"o":{"x":[0.333,0.333,0.333],"y":[0,0,0]},"t":96,"s":[100,100,100]},{"t":119,"s":[0,0,100]}]}},"ao":0,"ip":0,"op":120,"st":0,"bm":0}],"markers":[]}